MANIFEST.in
README.md
main.py
requirements.txt
setup.py
benchmark/benchmark.py
benchmark/plot.py
image_registration/__init__.py
image_registration/exceptions.py
image_registration/matching/__init__.py
image_registration/matching/keypoint/__init__.py
image_registration/matching/keypoint/base.py
image_registration/matching/keypoint/base.pyi
image_registration/matching/keypoint/akaze/__init__.py
image_registration/matching/keypoint/akaze/akaze.py
image_registration/matching/keypoint/akaze/akaze.pyi
image_registration/matching/keypoint/orb/__init__.py
image_registration/matching/keypoint/orb/orb.py
image_registration/matching/keypoint/orb/orb.pyi
image_registration/matching/keypoint/sift/__init__.py
image_registration/matching/keypoint/sift/sift.py
image_registration/matching/keypoint/sift/sift.pyi
image_registration/matching/keypoint/surf/__init__.py
image_registration/matching/keypoint/surf/surf.py
image_registration/matching/keypoint/surf/surf.pyi
image_registration/matching/template/__init__.py
image_registration/matching/template/matchTemplate.py
image_registration/matching/template/matchTemplate.pyi
image_registration/utils/__init__.py
image_registration/utils/__init__.pyi
py_image_registration.egg-info/PKG-INFO
py_image_registration.egg-info/SOURCES.txt
py_image_registration.egg-info/dependency_links.txt
py_image_registration.egg-info/requires.txt
py_image_registration.egg-info/top_level.txt