Metadata-Version: 2.1
Name: py-image-registration
Version: 2.0.0
Summary: image registration by ORB/SIFT/SURF/CUDA_SURF/ORB/CUDA_ORB/matchTemplate
Home-page: https://github.com/hakaboom/image_registration
Author: hakaboom
Author-email: 1534225986@qq.com
License: Apache License 2.0
Platform: UNKNOWN
Classifier: Programming Language :: Python :: 3
Classifier: License :: OSI Approved :: Apache Software License
Classifier: Operating System :: OS Independent
Requires-Python: >=3.5
